Metadata-Version: 1.0
Name: melax-nlp
Version: 0.0.1
Summary: nlp ner lib
Home-page: https://github.com/sodalvjian/melax_nlp_lib.git
Author: lj
Author-email: soda.lj@gmail.com
License: UNKNOWN
Platform: UNKNOWN
